LICENSE
MANIFEST.in
README.rst
setup.py
django_tmdb.egg-info/PKG-INFO
django_tmdb.egg-info/SOURCES.txt
django_tmdb.egg-info/dependency_links.txt
django_tmdb.egg-info/top_level.txt
tmdb/__init__.py
tmdb/tmdb.py