Metadata-Version: 1.1
Name: django-tmdb
Version: 0.1
Summary: A small TMDB (themoviedatabase) API v3 wrapper for Django.
Home-page: https://github.com/Merenon/django-tmdb
Author: Dennis Detering
Author-email: dennis@dety.eu
License: BEER-WARE License
Platform: UNKNOWN
Classifier: Environment :: Web Environment
Classifier: Framework :: Django
Classifier: Intended Audience :: Developers
Classifier: License :: Freeware
Classifier: Operating System :: OS Independent
Classifier: Programming Language :: Python
Classifier: Programming Language :: Python :: 2.7
Classifier: Topic :: Internet :: WWW/HTTP
Classifier: Topic :: Internet :: WWW/HTTP :: Dynamic Content
